tagvalidator/.DS_Store
tagvalidator/__init__.py
tagvalidator/events.py
tagvalidator/tagging_services.py
tagvalidator-0.1.1.dist-info/METADATA
tagvalidator-0.1.1.dist-info/WHEEL
tagvalidator-0.1.1.dist-info/RECORD
