Metadata-Version: 2.3
Name: tagvalidator
Version: 0.1.1
Summary: 
Author: Your Name
Author-email: you@example.com
Requires-Python: >=3.12
Classifier: Programming Language :: Python :: 3
Classifier: Programming Language :: Python :: 3.12
Classifier: Programming Language :: Python :: 3.13
Requires-Dist: blinker (==1.7.0)
Requires-Dist: selenium-wire (>=5.1.0,<6.0.0)
Requires-Dist: setuptools (>=80.9.0,<81.0.0)
Requires-Dist: webdriver-manager (>=4.0.2,<5.0.0)
